[{"url":"https://emirodgar.com/","name":"emirodgar_com_","file":"emirodgar_com_.report.json","score":"0.77"},{"url":"https://emirodgar.com/carrera-profesional/","name":"emirodgar_com_carrera-profesional_","file":"emirodgar_com_carrera-profesional_.report.json","score":0,"error":"Sat, 27 Apr 2019 18:02:56 GMT ChromeLauncher Waiting for browser.\nSat, 27 Apr 2019 18:02:56 GMT ChromeLauncher Waiting for browser...\nSat, 27 Apr 2019 18:02:57 GMT ChromeLauncher Waiting for browser...\u001b[32m√\u001b[0m\nSat, 27 Apr 2019 18:02:57 GMT status Connecting to browser\nSat, 27 Apr 2019 18:02:57 GMT status Resetting state with about:blank\nSat, 27 Apr 2019 18:02:58 GMT status Benchmarking machine\nSat, 27 Apr 2019 18:02:58 GMT status Initializing…\nSat, 27 Apr 2019 18:02:59 GMT status Loading page & waiting for onload CSSUsage, ViewportDimensions, RuntimeExceptions, ChromeConsoleMessages, Accessibility, AnchorElements, ImageElements, LinkElements, MetaElements, ScriptElements, AppCacheManifest, Doctype, DOMStats, JSLibraries, OptimizedImages, PasswordInputsWithPreventedPaste, ResponseCompression, TagsBlockingFirstPaint, FontSize, EmbeddedContent, RobotsTxt, TapTargets\nSat, 27 Apr 2019 18:03:08 GMT status Retrieving in-page: CSSUsage\nSat, 27 Apr 2019 18:03:08 GMT status Retrieving in-page: ViewportDimensions\nSat, 27 Apr 2019 18:03:08 GMT status Retrieving in-page: RuntimeExceptions\nSat, 27 Apr 2019 18:03:08 GMT status Retrieving in-page: ChromeConsoleMessages\nSat, 27 Apr 2019 18:03:08 GMT status Retrieving in-page: Accessibility\nSat, 27 Apr 2019 18:03:08 GMT status Retrieving in-page: AnchorElements\nSat, 27 Apr 2019 18:03:08 GMT status Retrieving in-page: ImageElements\nSat, 27 Apr 2019 18:03:08 GMT status Retrieving in-page: LinkElements\nSat, 27 Apr 2019 18:03:08 GMT status Retrieving in-page: MetaElements\nSat, 27 Apr 2019 18:03:08 GMT status Retrieving in-page: ScriptElements\nSat, 27 Apr 2019 18:03:08 GMT status Retrieving in-page: AppCacheManifest\nSat, 27 Apr 2019 18:03:08 GMT status Retrieving in-page: Doctype\nSat, 27 Apr 2019 18:03:08 GMT status Retrieving in-page: DOMStats\nSat, 27 Apr 2019 18:03:08 GMT status Retrieving in-page: JSLibraries\nSat, 27 Apr 2019 18:03:08 GMT status Retrieving in-page: OptimizedImages\nSat, 27 Apr 2019 18:03:08 GMT status Retrieving in-page: PasswordInputsWithPreventedPaste\nSat, 27 Apr 2019 18:03:08 GMT status Retrieving in-page: ResponseCompression\nSat, 27 Apr 2019 18:03:08 GMT status Retrieving in-page: TagsBlockingFirstPaint\nSat, 27 Apr 2019 18:03:08 GMT status Retrieving in-page: FontSize\nSat, 27 Apr 2019 18:03:08 GMT status Retrieving in-page: EmbeddedContent\nSat, 27 Apr 2019 18:03:08 GMT status Retrieving in-page: RobotsTxt\nSat, 27 Apr 2019 18:03:08 GMT status Retrieving in-page: TapTargets\nSat, 27 Apr 2019 18:03:08 GMT status Retrieving trace\nSat, 27 Apr 2019 18:03:08 GMT status Retrieving devtoolsLog & network records\nSat, 27 Apr 2019 18:03:08 GMT status Retrieving: CSSUsage\nSat, 27 Apr 2019 18:03:08 GMT status Retrieving: ViewportDimensions\nSat, 27 Apr 2019 18:03:08 GMT status Retrieving: RuntimeExceptions\nSat, 27 Apr 2019 18:03:08 GMT status Retrieving: ChromeConsoleMessages\nSat, 27 Apr 2019 18:03:08 GMT status Retrieving: Accessibility\nSat, 27 Apr 2019 18:03:08 GMT status Retrieving: AnchorElements\nSat, 27 Apr 2019 18:03:08 GMT status Retrieving: ImageElements\nSat, 27 Apr 2019 18:03:08 GMT status Retrieving: LinkElements\nSat, 27 Apr 2019 18:03:08 GMT status Retrieving: MetaElements\nSat, 27 Apr 2019 18:03:08 GMT status Retrieving: ScriptElements\nSat, 27 Apr 2019 18:03:08 GMT status Retrieving: AppCacheManifest\nSat, 27 Apr 2019 18:03:08 GMT status Retrieving: Doctype\nSat, 27 Apr 2019 18:03:08 GMT status Retrieving: DOMStats\nSat, 27 Apr 2019 18:03:08 GMT status Retrieving: JSLibraries\nSat, 27 Apr 2019 18:03:08 GMT status Retrieving: OptimizedImages\nSat, 27 Apr 2019 18:03:10 GMT status Retrieving: PasswordInputsWithPreventedPaste\nSat, 27 Apr 2019 18:03:10 GMT status Retrieving: ResponseCompression\nSat, 27 Apr 2019 18:03:10 GMT status Retrieving: TagsBlockingFirstPaint\nSat, 27 Apr 2019 18:03:10 GMT status Retrieving: FontSize\nSat, 27 Apr 2019 18:03:10 GMT status Retrieving: EmbeddedContent\nSat, 27 Apr 2019 18:03:10 GMT status Retrieving: RobotsTxt\nSat, 27 Apr 2019 18:03:10 GMT status Retrieving: TapTargets\nSat, 27 Apr 2019 18:03:10 GMT status Resetting state with about:blank\nSat, 27 Apr 2019 18:03:10 GMT status Loading page & waiting for onload ServiceWorker, Offline, StartUrl\nSat, 27 Apr 2019 18:03:10 GMT status Retrieving in-page: ServiceWorker\nSat, 27 Apr 2019 18:03:10 GMT status Retrieving in-page: Offline\nSat, 27 Apr 2019 18:03:10 GMT status Retrieving in-page: StartUrl\nSat, 27 Apr 2019 18:03:10 GMT status Retrieving devtoolsLog & network records\nSat, 27 Apr 2019 18:03:10 GMT status Retrieving: ServiceWorker\nSat, 27 Apr 2019 18:03:10 GMT status Retrieving: Offline\nSat, 27 Apr 2019 18:03:10 GMT status Retrieving: StartUrl\nSat, 27 Apr 2019 18:03:10 GMT status Resetting state with about:blank\nSat, 27 Apr 2019 18:03:10 GMT status Loading page & waiting for onload HTTPRedirect, HTMLWithoutJavaScript\nSat, 27 Apr 2019 18:03:11 GMT status Retrieving in-page: HTTPRedirect\nSat, 27 Apr 2019 18:03:11 GMT status Retrieving in-page: HTMLWithoutJavaScript\nSat, 27 Apr 2019 18:03:11 GMT status Retrieving devtoolsLog & network records\nSat, 27 Apr 2019 18:03:11 GMT status Retrieving: HTTPRedirect\nSat, 27 Apr 2019 18:03:11 GMT status Retrieving: HTMLWithoutJavaScript\nSat, 27 Apr 2019 18:03:11 GMT status Disconnecting from browser...\nSat, 27 Apr 2019 18:03:11 GMT status Analyzing and running audits...\nSat, 27 Apr 2019 18:03:11 GMT status Evaluating: Uses HTTPS\nSat, 27 Apr 2019 18:03:11 GMT status Evaluating: Redirects HTTP traffic to HTTPS\nSat, 27 Apr 2019 18:03:11 GMT status Evaluating: Registers a service worker that controls page and start_url\nSat, 27 Apr 2019 18:03:11 GMT status Evaluating: Current page responds with a 200 when offline\nSat, 27 Apr 2019 18:03:11 GMT status Evaluating: Has a `<meta name=\"viewport\">` tag with `width` or `initial-scale`\nSat, 27 Apr 2019 18:03:11 GMT status Evaluating: Contains some content when JavaScript is not available\nSat, 27 Apr 2019 18:03:11 GMT status Evaluating: First Contentful Paint\nSat, 27 Apr 2019 18:03:11 GMT status Evaluating: First Meaningful Paint\nSat, 27 Apr 2019 18:03:11 GMT status Evaluating: Page load is fast enough on mobile networks\nSat, 27 Apr 2019 18:03:11 GMT status Evaluating: Speed Index\nSat, 27 Apr 2019 18:03:11 GMT status Evaluating: Screenshot Thumbnails\nSat, 27 Apr 2019 18:03:11 GMT status Evaluating: Final Screenshot\nSat, 27 Apr 2019 18:03:11 GMT status Evaluating: Estimated Input Latency\nSat, 27 Apr 2019 18:03:11 GMT status Evaluating: Max Potential FID\nSat, 27 Apr 2019 18:03:11 GMT status Evaluating: No browser errors logged to the console\nSat, 27 Apr 2019 18:03:11 GMT status Evaluating: Server response times are low (TTFB)\nSat, 27 Apr 2019 18:03:11 GMT status Evaluating: First CPU Idle\nSat, 27 Apr 2019 18:03:11 GMT status Evaluating: Time to Interactive\nSat, 27 Apr 2019 18:03:11 GMT status Evaluating: User Timing marks and measures\nSat, 27 Apr 2019 18:03:11 GMT status Evaluating: Minimize Critical Requests Depth\nSat, 27 Apr 2019 18:03:11 GMT status Evaluating: Avoid multiple page redirects\nSat, 27 Apr 2019 18:03:11 GMT status Evaluating: Web app manifest meets the installability requirements\nSat, 27 Apr 2019 18:03:11 GMT status Evaluating: Configured for a custom splash screen\nSat, 27 Apr 2019 18:03:11 GMT status Evaluating: Sets an address-bar theme color\nSat, 27 Apr 2019 18:03:11 GMT status Evaluating: Content is sized correctly for the viewport\nSat, 27 Apr 2019 18:03:11 GMT status Evaluating: Displays images with correct aspect ratio\nSat, 27 Apr 2019 18:03:11 GMT status Evaluating: Avoids deprecated APIs\nSat, 27 Apr 2019 18:03:11 GMT status Evaluating: Minimizes main-thread work\nSat, 27 Apr 2019 18:03:11 GMT status Evaluating: JavaScript execution time\nSat, 27 Apr 2019 18:03:11 GMT status Evaluating: Preload key requests\nSat, 27 Apr 2019 18:03:11 GMT status Evaluating: Preconnect to required origins\nSat, 27 Apr 2019 18:03:11 GMT status Evaluating: All text remains visible during webfont loads\nSat, 27 Apr 2019 18:03:11 GMT status Evaluating: Diagnostics\nSat, 27 Apr 2019 18:03:11 GMT status Evaluating: Network Requests\nSat, 27 Apr 2019 18:03:11 GMT status Evaluating: Network Round Trip Times\nSat, 27 Apr 2019 18:03:11 GMT status Evaluating: Server Backend Latencies\nSat, 27 Apr 2019 18:03:11 GMT status Evaluating: Tasks\nSat, 27 Apr 2019 18:03:11 GMT status Evaluating: Metrics\nSat, 27 Apr 2019 18:03:11 GMT status Evaluating: start_url responds with a 200 when offline\nSat, 27 Apr 2019 18:03:11 GMT status Evaluating: Site works cross-browser\nSat, 27 Apr 2019 18:03:11 GMT status Evaluating: Page transitions don't feel like they block on the network\nSat, 27 Apr 2019 18:03:11 GMT status Evaluating: Each page has a URL\nSat, 27 Apr 2019 18:03:11 GMT status Evaluating: `[accesskey]` values are unique\nSat, 27 Apr 2019 18:03:11 GMT status Evaluating: `[aria-*]` attributes match their roles\nSat, 27 Apr 2019 18:03:11 GMT status Evaluating: `[role]`s have all required `[aria-*]` attributes\nSat, 27 Apr 2019 18:03:11 GMT status Evaluating: Elements with `[role]` that require specific children `[role]`s, are present\nSat, 27 Apr 2019 18:03:11 GMT status Evaluating: `[role]`s are contained by their required parent element\nSat, 27 Apr 2019 18:03:11 GMT status Evaluating: `[role]` values are valid\nSat, 27 Apr 2019 18:03:11 GMT status Evaluating: `[aria-*]` attributes have valid values\nSat, 27 Apr 2019 18:03:11 GMT status Evaluating: `[aria-*]` attributes are valid and not misspelled\nSat, 27 Apr 2019 18:03:11 GMT status Evaluating: `<audio>` elements contain a `<track>` element with `[kind=\"captions\"]`\nSat, 27 Apr 2019 18:03:11 GMT status Evaluating: Buttons have an accessible name\nSat, 27 Apr 2019 18:03:11 GMT status Evaluating: The page contains a heading, skip link, or landmark region\nSat, 27 Apr 2019 18:03:11 GMT status Evaluating: Background and foreground colors have a sufficient contrast ratio\nSat, 27 Apr 2019 18:03:11 GMT status Evaluating: `<dl>`'s contain only properly-ordered `<dt>` and `<dd>` groups, `<script>` or `<template>` elements.\nSat, 27 Apr 2019 18:03:11 GMT status Evaluating: Definition list items are wrapped in `<dl>` elements\nSat, 27 Apr 2019 18:03:11 GMT status Evaluating: Document has a `<title>` element\nSat, 27 Apr 2019 18:03:11 GMT status Evaluating: `[id]` attributes on the page are unique\nSat, 27 Apr 2019 18:03:11 GMT status Evaluating: `<frame>` or `<iframe>` elements have a title\nSat, 27 Apr 2019 18:03:11 GMT status Evaluating: `<html>` element has a `[lang]` attribute\nSat, 27 Apr 2019 18:03:11 GMT status Evaluating: `<html>` element has a valid value for its `[lang]` attribute\nSat, 27 Apr 2019 18:03:11 GMT status Evaluating: Image elements have `[alt]` attributes\nSat, 27 Apr 2019 18:03:11 GMT status Evaluating: `<input type=\"image\">` elements have `[alt]` text\nSat, 27 Apr 2019 18:03:11 GMT status Evaluating: Form elements have associated labels\nSat, 27 Apr 2019 18:03:11 GMT status Evaluating: Presentational `<table>` elements avoid using `<th>`, `<caption>` or the `[summary]` attribute.\nSat, 27 Apr 2019 18:03:11 GMT status Evaluating: Links have a discernible name\nSat, 27 Apr 2019 18:03:11 GMT status Evaluating: Lists contain only `<li>` elements and script supporting elements (`<script>` and `<template>`).\nSat, 27 Apr 2019 18:03:11 GMT status Evaluating: List items (`<li>`) are contained within `<ul>` or `<ol>` parent elements\nSat, 27 Apr 2019 18:03:11 GMT status Evaluating: The document does not use `<meta http-equiv=\"refresh\">`\nSat, 27 Apr 2019 18:03:11 GMT status Evaluating: `[user-scalable=\"no\"]` is not used in the `<meta name=\"viewport\">` element and the `[maximum-scale]` attribute is not less than 5.\nSat, 27 Apr 2019 18:03:11 GMT status Evaluating: `<object>` elements have `[alt]` text\nSat, 27 Apr 2019 18:03:11 GMT status Evaluating: No element has a `[tabindex]` value greater than 0\nSat, 27 Apr 2019 18:03:11 GMT status Evaluating: Cells in a `<table>` element that use the `[headers]` attribute only refer to other cells of that same table.\nSat, 27 Apr 2019 18:03:11 GMT status Evaluating: `<th>` elements and elements with `[role=\"columnheader\"/\"rowheader\"]` have data cells they describe.\nSat, 27 Apr 2019 18:03:11 GMT status Evaluating: `[lang]` attributes have a valid value\nSat, 27 Apr 2019 18:03:11 GMT status Evaluating: `<video>` elements contain a `<track>` element with `[kind=\"captions\"]`\nSat, 27 Apr 2019 18:03:11 GMT status Evaluating: `<video>` elements contain a `<track>` element with `[kind=\"description\"]`\nSat, 27 Apr 2019 18:03:11 GMT status Evaluating: Custom controls have associated labels\nSat, 27 Apr 2019 18:03:11 GMT status Evaluating: Custom controls have ARIA roles\nSat, 27 Apr 2019 18:03:11 GMT status Evaluating: User focus is not accidentally trapped in a region\nSat, 27 Apr 2019 18:03:11 GMT status Evaluating: Interactive controls are keyboard focusable\nSat, 27 Apr 2019 18:03:11 GMT status Evaluating: Headings don't skip levels\nSat, 27 Apr 2019 18:03:11 GMT status Evaluating: Interactive elements indicate their purpose and state\nSat, 27 Apr 2019 18:03:11 GMT status Evaluating: The page has a logical tab order\nSat, 27 Apr 2019 18:03:11 GMT status Evaluating: The user's focus is directed to new content added to the page\nSat, 27 Apr 2019 18:03:11 GMT status Evaluating: Offscreen content is hidden from assistive technology\nSat, 27 Apr 2019 18:03:11 GMT status Evaluating: HTML5 landmark elements are used to improve navigation\nSat, 27 Apr 2019 18:03:11 GMT status Evaluating: Visual order on the page follows DOM order\nSat, 27 Apr 2019 18:03:11 GMT status Evaluating: Uses efficient cache policy on static assets\nSat, 27 Apr 2019 18:03:11 GMT status Evaluating: Avoids enormous network payloads\nSat, 27 Apr 2019 18:03:11 GMT status Evaluating: Defer offscreen images\nSat, 27 Apr 2019 18:03:11 GMT status Evaluating: Eliminate render-blocking resources\nSat, 27 Apr 2019 18:03:11 GMT status Evaluating: Minify CSS\nSat, 27 Apr 2019 18:03:11 GMT status Evaluating: Minify JavaScript\nSat, 27 Apr 2019 18:03:12 GMT status Evaluating: Remove unused CSS\nSat, 27 Apr 2019 18:03:12 GMT status Evaluating: Serve images in next-gen formats\nSat, 27 Apr 2019 18:03:12 GMT status Evaluating: Efficiently encode images\nSat, 27 Apr 2019 18:03:12 GMT status Evaluating: Enable text compression\nSat, 27 Apr 2019 18:03:12 GMT status Evaluating: Properly size images\nSat, 27 Apr 2019 18:03:12 GMT status Evaluating: Use video formats for animated content\nSat, 27 Apr 2019 18:03:12 GMT status Evaluating: Avoids Application Cache\nSat, 27 Apr 2019 18:03:12 GMT status Evaluating: Page has the HTML doctype\nSat, 27 Apr 2019 18:03:12 GMT status Evaluating: Avoids an excessive DOM size\nSat, 27 Apr 2019 18:03:12 GMT status Evaluating: Links to cross-origin destinations are safe\nSat, 27 Apr 2019 18:03:12 GMT status Evaluating: Avoids requesting the geolocation permission on page load\nSat, 27 Apr 2019 18:03:12 GMT status Evaluating: Avoids `document.write()`\nSat, 27 Apr 2019 18:03:12 GMT status Evaluating: Avoids front-end JavaScript libraries with known security vulnerabilities\nSat, 27 Apr 2019 18:03:12 GMT status Evaluating: Detected JavaScript libraries\nSat, 27 Apr 2019 18:03:12 GMT status Evaluating: Avoids requesting the notification permission on page load\nSat, 27 Apr 2019 18:03:12 GMT status Evaluating: Allows users to paste into password fields\nSat, 27 Apr 2019 18:03:12 GMT status Evaluating: Uses HTTP/2 for its own resources\nSat, 27 Apr 2019 18:03:12 GMT status Evaluating: Uses passive listeners to improve scrolling performance\nSat, 27 Apr 2019 18:03:12 GMT status Evaluating: Document has a meta description\nSat, 27 Apr 2019 18:03:12 GMT status Evaluating: Page has successful HTTP status code\nSat, 27 Apr 2019 18:03:12 GMT status Evaluating: Document uses legible font sizes\nSat, 27 Apr 2019 18:03:12 GMT status Evaluating: Links have descriptive text\nSat, 27 Apr 2019 18:03:12 GMT status Evaluating: Page isn’t blocked from indexing\nSat, 27 Apr 2019 18:03:12 GMT status Evaluating: robots.txt is valid\nSat, 27 Apr 2019 18:03:12 GMT status Evaluating: Tap targets are sized appropriately\nSat, 27 Apr 2019 18:03:12 GMT status Evaluating: Document has a valid `hreflang`\nSat, 27 Apr 2019 18:03:12 GMT status Evaluating: Document avoids plugins\nSat, 27 Apr 2019 18:03:12 GMT status Evaluating: Document has a valid `rel=canonical`\nSat, 27 Apr 2019 18:03:12 GMT status Evaluating: Structured data is valid\nSat, 27 Apr 2019 18:03:12 GMT status Generating results...\nSat, 27 Apr 2019 18:03:12 GMT Printer json output written to C:/wamp/www/emirodgar-com/rendimiento/json/emirodgar_com_carrera-profesional_.report.json\nSat, 27 Apr 2019 18:03:12 GMT ChromeLauncher Killing Chrome instance 9316\nERROR: el proceso con PID 10960 (proceso secundario de PID 9316)\r\nno se pudo terminar.\r\nMotivo: No hay ninguna instancia activa de la tarea.\r\r\nERROR: el proceso con PID 12156 (proceso secundario de PID 9316)\r\nno se pudo terminar.\r\nMotivo: No hay ninguna instancia activa de la tarea.\r\r\nERROR: el proceso con PID 14240 (proceso secundario de PID 9316)\r\nno se pudo terminar.\r\nMotivo: No hay ninguna instancia activa de la tarea.\r\r\nSat, 27 Apr 2019 18:03:12 GMT ChromeLauncher:warn Chrome could not be killed Command failed: taskkill /pid 9316 /T /F\nERROR: el proceso con PID 10960 (proceso secundario de PID 9316)\r\nno se pudo terminar.\r\nMotivo: No hay ninguna instancia activa de la tarea.\r\r\nERROR: el proceso con PID 12156 (proceso secundario de PID 9316)\r\nno se pudo terminar.\r\nMotivo: No hay ninguna instancia activa de la tarea.\r\r\nERROR: el proceso con PID 14240 (proceso secundario de PID 9316)\r\nno se pudo terminar.\r\nMotivo: No hay ninguna instancia activa de la tarea.\r\r\n\nSat, 27 Apr 2019 18:03:12 GMT ChromeLauncher Killing Chrome instance 9316\nERROR: el proceso con PID 9316 (proceso secundario de PID 820)\r\nno se pudo terminar.\r\nMotivo: No hay ninguna instancia activa de la tarea.\r\r\nSat, 27 Apr 2019 18:03:12 GMT ChromeLauncher:warn Chrome could not be killed Command failed: taskkill /pid 9316 /T /F\nERROR: el proceso con PID 9316 (proceso secundario de PID 820)\r\nno se pudo terminar.\r\nMotivo: No hay ninguna instancia activa de la tarea.\r\r\n\nRuntime error encountered: Couldn't quit Chrome process. Error: Chrome could not be killed Command failed: taskkill /pid 9316 /T /F\nERROR: el proceso con PID 10960 (proceso secundario de PID 9316)\r\nno se pudo terminar.\r\nMotivo: No hay ninguna instancia activa de la tarea.\r\r\nERROR: el proceso con PID 12156 (proceso secundario de PID 9316)\r\nno se pudo terminar.\r\nMotivo: No hay ninguna instancia activa de la tarea.\r\r\nERROR: el proceso con PID 14240 (proceso secundario de PID 9316)\r\nno se pudo terminar.\r\nMotivo: No hay ninguna instancia activa de la tarea.\r\r\n\nError: Couldn't quit Chrome process. Error: Chrome could not be killed Command failed: taskkill /pid 9316 /T /F\nERROR: el proceso con PID 10960 (proceso secundario de PID 9316)\r\nno se pudo terminar.\r\nMotivo: No hay ninguna instancia activa de la tarea.\r\r\nERROR: el proceso con PID 12156 (proceso secundario de PID 9316)\r\nno se pudo terminar.\r\nMotivo: No hay ninguna instancia activa de la tarea.\r\r\nERROR: el proceso con PID 14240 (proceso secundario de PID 9316)\r\nno se pudo terminar.\r\nMotivo: No hay ninguna instancia activa de la tarea.\r\r\n\n    at Promise.race.catch.err (C:\\Users\\Emilio\\AppData\\Roaming\\npm\\node_modules\\lighthouse\\lighthouse-cli\\run.js:178:11)\n    at process._tickCallback (internal/process/next_tick.js:68:7)\n"},{"url":"https://emirodgar.com/asesor-seo/","name":"emirodgar_com_asesor-seo_","file":"emirodgar_com_asesor-seo_.report.json","score":"0.77"},{"url":"https://emirodgar.com/consultor-seo/","name":"emirodgar_com_consultor-seo_","file":"emirodgar_com_consultor-seo_.report.json","score":"0.63"},{"url":"https://emirodgar.com/recursos-marketing-digital/","name":"emirodgar_com_recursos-marketing-digital_","file":"emirodgar_com_recursos-marketing-digital_.report.json","score":0,"error":"Sat, 27 Apr 2019 18:04:29 GMT ChromeLauncher Waiting for browser.\nSat, 27 Apr 2019 18:04:29 GMT ChromeLauncher Waiting for browser...\nSat, 27 Apr 2019 18:04:30 GMT ChromeLauncher Waiting for browser.....\nSat, 27 Apr 2019 18:04:31 GMT ChromeLauncher Waiting for browser.....\u001b[32m√\u001b[0m\nSat, 27 Apr 2019 18:05:32 GMT status Connecting to browser\nSat, 27 Apr 2019 18:05:32 GMT status Resetting state with about:blank\nSat, 27 Apr 2019 18:05:32 GMT status Benchmarking machine\nSat, 27 Apr 2019 18:05:33 GMT status Initializing…\nSat, 27 Apr 2019 18:05:34 GMT status Loading page & waiting for onload CSSUsage, ViewportDimensions, RuntimeExceptions, ChromeConsoleMessages, Accessibility, AnchorElements, ImageElements, LinkElements, MetaElements, ScriptElements, AppCacheManifest, Doctype, DOMStats, JSLibraries, OptimizedImages, PasswordInputsWithPreventedPaste, ResponseCompression, TagsBlockingFirstPaint, FontSize, EmbeddedContent, RobotsTxt, TapTargets\nSat, 27 Apr 2019 18:05:49 GMT status Disconnecting from browser...\nSat, 27 Apr 2019 18:05:49 GMT ChromeLauncher Killing Chrome instance 3172\nevents.js:174\r\n      throw er; // Unhandled 'error' event\r\n      ^\r\n\r\nError: read ECONNRESET\r\n    at TCP.onStreamRead (internal/stream_base_commons.js:111:27)\r\nEmitted 'error' event at:\r\n    at Socket.socketErrorListener (_http_client.js:392:9)\r\n    at Socket.emit (events.js:189:13)\r\n    at emitErrorNT (internal/streams/destroy.js:82:8)\r\n    at emitErrorAndCloseNT (internal/streams/destroy.js:50:3)\r\n    at process._tickCallback (internal/process/next_tick.js:63:19)\r\n"},{"url":"https://emirodgar.com/consultor-seo/salamanca","name":"emirodgar_com_consultor-seo_salamanca","file":"emirodgar_com_consultor-seo_salamanca.report.json","score":0,"error":"Sat, 27 Apr 2019 18:23:08 GMT ChromeLauncher Waiting for browser.\nSat, 27 Apr 2019 18:23:09 GMT ChromeLauncher Waiting for browser...\nSat, 27 Apr 2019 18:23:17 GMT ChromeLauncher Waiting for browser.....\nSat, 27 Apr 2019 18:23:19 GMT ChromeLauncher Waiting for browser.......\nSat, 27 Apr 2019 18:23:20 GMT ChromeLauncher Waiting for browser.........\nSat, 27 Apr 2019 18:23:22 GMT ChromeLauncher Waiting for browser...........\nSat, 27 Apr 2019 18:23:25 GMT ChromeLauncher Waiting for browser.............\nSat, 27 Apr 2019 18:23:25 GMT ChromeLauncher Waiting for browser.............\u001b[32m√\u001b[0m\nSat, 27 Apr 2019 18:26:54 GMT status Connecting to browser\nSat, 27 Apr 2019 18:27:06 GMT status Resetting state with about:blank\nSat, 27 Apr 2019 18:27:08 GMT status Benchmarking machine\nSat, 27 Apr 2019 18:27:09 GMT status Initializing…\nSat, 27 Apr 2019 18:27:14 GMT status Loading page & waiting for onload CSSUsage, ViewportDimensions, RuntimeExceptions, ChromeConsoleMessages, Accessibility, AnchorElements, ImageElements, LinkElements, MetaElements, ScriptElements, AppCacheManifest, Doctype, DOMStats, JSLibraries, OptimizedImages, PasswordInputsWithPreventedPaste, ResponseCompression, TagsBlockingFirstPaint, FontSize, EmbeddedContent, RobotsTxt, TapTargets\nSat, 27 Apr 2019 18:27:34 GMT status Disconnecting from browser...\nSat, 27 Apr 2019 18:27:34 GMT ChromeLauncher Killing Chrome instance 15416\nevents.js:174\r\n      throw er; // Unhandled 'error' event\r\n      ^\r\n\r\nError: read ECONNRESET\r\n    at TCP.onStreamRead (internal/stream_base_commons.js:111:27)\r\nEmitted 'error' event at:\r\n    at Socket.socketErrorListener (_http_client.js:392:9)\r\n    at Socket.emit (events.js:189:13)\r\n    at emitErrorNT (internal/streams/destroy.js:82:8)\r\n    at emitErrorAndCloseNT (internal/streams/destroy.js:50:3)\r\n    at process._tickCallback (internal/process/next_tick.js:63:19)\r\n"},{"url":"https://emirodgar.com/consultor-seo/argentina","name":"emirodgar_com_consultor-seo_argentina","file":"emirodgar_com_consultor-seo_argentina.report.json","score":0,"error":"Sat, 27 Apr 2019 18:28:58 GMT ChromeLauncher Waiting for browser.\nSat, 27 Apr 2019 18:28:58 GMT ChromeLauncher Waiting for browser...\nSat, 27 Apr 2019 18:28:59 GMT ChromeLauncher Waiting for browser.....\nSat, 27 Apr 2019 18:29:01 GMT ChromeLauncher Waiting for browser.......\nSat, 27 Apr 2019 18:29:02 GMT ChromeLauncher Waiting for browser.........\nSat, 27 Apr 2019 18:29:03 GMT ChromeLauncher Waiting for browser.........\u001b[32m√\u001b[0m\nSat, 27 Apr 2019 18:29:33 GMT status Connecting to browser\nSat, 27 Apr 2019 18:29:36 GMT status Resetting state with about:blank\nSat, 27 Apr 2019 18:29:42 GMT status Benchmarking machine\nSat, 27 Apr 2019 18:29:43 GMT status Initializing…\nSat, 27 Apr 2019 18:29:45 GMT status Loading page & waiting for onload CSSUsage, ViewportDimensions, RuntimeExceptions, ChromeConsoleMessages, Accessibility, AnchorElements, ImageElements, LinkElements, MetaElements, ScriptElements, AppCacheManifest, Doctype, DOMStats, JSLibraries, OptimizedImages, PasswordInputsWithPreventedPaste, ResponseCompression, TagsBlockingFirstPaint, FontSize, EmbeddedContent, RobotsTxt, TapTargets\nSat, 27 Apr 2019 18:30:02 GMT status Disconnecting from browser...\nSat, 27 Apr 2019 18:30:02 GMT ChromeLauncher Killing Chrome instance 7144\nevents.js:174\r\n      throw er; // Unhandled 'error' event\r\n      ^\r\n\r\nError: write ECONNRESET\r\n    at afterWriteDispatched (internal/stream_base_commons.js:78:25)\r\n    at writeGeneric (internal/stream_base_commons.js:73:3)\r\n    at Socket._writeGeneric (net.js:707:5)\r\n    at Socket.connect (net.js:689:12)\r\n    at Object.onceWrapper (events.js:277:13)\r\n    at Socket.emit (events.js:194:15)\r\n    at TCPConnectWrap.afterConnect [as oncomplete] (net.js:1090:10)\r\nEmitted 'error' event at:\r\n    at Socket.socketErrorListener (_http_client.js:392:9)\r\n    at Socket.emit (events.js:189:13)\r\n    at onwriteError (_stream_writable.js:431:12)\r\n    at onwrite (_stream_writable.js:456:5)\r\n    at _destroy (internal/streams/destroy.js:40:7)\r\n    at Socket._destroy (net.js:607:3)\r\n    at Socket.destroy (internal/streams/destroy.js:32:8)\r\n    at afterWriteDispatched (internal/stream_base_commons.js:78:17)\r\n    at writeGeneric (internal/stream_base_commons.js:73:3)\r\n    at Socket._writeGeneric (net.js:707:5)\r\n"},{"url":"https://emirodgar.com/consultor-seo/mexico","name":"emirodgar_com_consultor-seo_mexico","file":"emirodgar_com_consultor-seo_mexico.report.json","score":0,"error":"Sat, 27 Apr 2019 18:30:58 GMT ChromeLauncher Waiting for browser.\nSat, 27 Apr 2019 18:30:58 GMT ChromeLauncher Waiting for browser...\nSat, 27 Apr 2019 18:30:59 GMT ChromeLauncher Waiting for browser.....\nSat, 27 Apr 2019 18:31:01 GMT ChromeLauncher Waiting for browser.......\nSat, 27 Apr 2019 18:31:02 GMT ChromeLauncher Waiting for browser.........\nSat, 27 Apr 2019 18:31:03 GMT ChromeLauncher Waiting for browser.........\u001b[32m√\u001b[0m\nSat, 27 Apr 2019 18:31:45 GMT status Connecting to browser\nSat, 27 Apr 2019 18:31:50 GMT status Resetting state with about:blank\nSat, 27 Apr 2019 18:32:03 GMT status Benchmarking machine\nSat, 27 Apr 2019 18:32:04 GMT status Initializing…\nSat, 27 Apr 2019 18:32:07 GMT status Loading page & waiting for onload CSSUsage, ViewportDimensions, RuntimeExceptions, ChromeConsoleMessages, Accessibility, AnchorElements, ImageElements, LinkElements, MetaElements, ScriptElements, AppCacheManifest, Doctype, DOMStats, JSLibraries, OptimizedImages, PasswordInputsWithPreventedPaste, ResponseCompression, TagsBlockingFirstPaint, FontSize, EmbeddedContent, RobotsTxt, TapTargets\nSat, 27 Apr 2019 18:32:25 GMT status Disconnecting from browser...\nSat, 27 Apr 2019 18:32:25 GMT ChromeLauncher Killing Chrome instance 8544\nevents.js:174\r\n      throw er; // Unhandled 'error' event\r\n      ^\r\n\r\nError: read ECONNRESET\r\n    at TCP.onStreamRead (internal/stream_base_commons.js:111:27)\r\nEmitted 'error' event at:\r\n    at Socket.socketErrorListener (_http_client.js:392:9)\r\n    at Socket.emit (events.js:189:13)\r\n    at emitErrorNT (internal/streams/destroy.js:82:8)\r\n    at emitErrorAndCloseNT (internal/streams/destroy.js:50:3)\r\n    at process._tickCallback (internal/process/next_tick.js:63:19)\r\n"},{"url":"https://emirodgar.com/cv-starwars/","name":"emirodgar_com_cv-starwars_","file":"emirodgar_com_cv-starwars_.report.json","score":"0.58"},{"url":"https://emirodgar.com/mapa-web","name":"emirodgar_com_mapa-web","file":"emirodgar_com_mapa-web.report.json","score":0,"error":"Sat, 27 Apr 2019 18:35:40 GMT ChromeLauncher Waiting for browser.\nSat, 27 Apr 2019 18:35:40 GMT ChromeLauncher Waiting for browser...\nSat, 27 Apr 2019 18:35:43 GMT ChromeLauncher Waiting for browser.....\nSat, 27 Apr 2019 18:35:45 GMT ChromeLauncher Waiting for browser.......\nSat, 27 Apr 2019 18:35:46 GMT ChromeLauncher Waiting for browser.........\nSat, 27 Apr 2019 18:35:48 GMT ChromeLauncher Waiting for browser...........\nSat, 27 Apr 2019 18:35:49 GMT ChromeLauncher Waiting for browser.............\nSat, 27 Apr 2019 18:35:50 GMT ChromeLauncher Waiting for browser.............\u001b[32m√\u001b[0m\nSat, 27 Apr 2019 18:36:36 GMT status Connecting to browser\nSat, 27 Apr 2019 18:36:42 GMT status Resetting state with about:blank\nSat, 27 Apr 2019 18:36:58 GMT status Benchmarking machine\nSat, 27 Apr 2019 18:36:59 GMT status Initializing…\nSat, 27 Apr 2019 18:37:03 GMT status Loading page & waiting for onload CSSUsage, ViewportDimensions, RuntimeExceptions, ChromeConsoleMessages, Accessibility, AnchorElements, ImageElements, LinkElements, MetaElements, ScriptElements, AppCacheManifest, Doctype, DOMStats, JSLibraries, OptimizedImages, PasswordInputsWithPreventedPaste, ResponseCompression, TagsBlockingFirstPaint, FontSize, EmbeddedContent, RobotsTxt, TapTargets\nSat, 27 Apr 2019 18:37:21 GMT status Disconnecting from browser...\nSat, 27 Apr 2019 18:37:21 GMT ChromeLauncher Killing Chrome instance 11664\nevents.js:174\r\n      throw er; // Unhandled 'error' event\r\n      ^\r\n\r\nError: read ECONNRESET\r\n    at TCP.onStreamRead (internal/stream_base_commons.js:111:27)\r\nEmitted 'error' event at:\r\n    at Socket.socketErrorListener (_http_client.js:392:9)\r\n    at Socket.emit (events.js:189:13)\r\n    at emitErrorNT (internal/streams/destroy.js:82:8)\r\n    at emitErrorAndCloseNT (internal/streams/destroy.js:50:3)\r\n    at process._tickCallback (internal/process/next_tick.js:63:19)\r\n"},{"url":"https://emirodgar.com/publicaciones","name":"emirodgar_com_publicaciones","file":"emirodgar_com_publicaciones.report.json","score":0,"error":"Sat, 27 Apr 2019 18:37:55 GMT ChromeLauncher Waiting for browser.\nSat, 27 Apr 2019 18:37:55 GMT ChromeLauncher Waiting for browser...\nSat, 27 Apr 2019 18:37:57 GMT ChromeLauncher Waiting for browser.....\nSat, 27 Apr 2019 18:37:58 GMT ChromeLauncher Waiting for browser.......\nSat, 27 Apr 2019 18:38:00 GMT ChromeLauncher Waiting for browser.........\nSat, 27 Apr 2019 18:38:00 GMT ChromeLauncher Waiting for browser.........\u001b[32m√\u001b[0m\nSat, 27 Apr 2019 18:38:26 GMT status Connecting to browser\nSat, 27 Apr 2019 18:38:32 GMT status Resetting state with about:blank\nSat, 27 Apr 2019 18:38:33 GMT status Benchmarking machine\nSat, 27 Apr 2019 18:38:34 GMT status Initializing…\nSat, 27 Apr 2019 18:38:36 GMT status Loading page & waiting for onload CSSUsage, ViewportDimensions, RuntimeExceptions, ChromeConsoleMessages, Accessibility, AnchorElements, ImageElements, LinkElements, MetaElements, ScriptElements, AppCacheManifest, Doctype, DOMStats, JSLibraries, OptimizedImages, PasswordInputsWithPreventedPaste, ResponseCompression, TagsBlockingFirstPaint, FontSize, EmbeddedContent, RobotsTxt, TapTargets\nSat, 27 Apr 2019 18:38:54 GMT status Disconnecting from browser...\nSat, 27 Apr 2019 18:38:54 GMT ChromeLauncher Killing Chrome instance 11840\nevents.js:174\r\n      throw er; // Unhandled 'error' event\r\n      ^\r\n\r\nError: read ECONNRESET\r\n    at TCP.onStreamRead (internal/stream_base_commons.js:111:27)\r\nEmitted 'error' event at:\r\n    at Socket.socketErrorListener (_http_client.js:392:9)\r\n    at Socket.emit (events.js:189:13)\r\n    at emitErrorNT (internal/streams/destroy.js:82:8)\r\n    at emitErrorAndCloseNT (internal/streams/destroy.js:50:3)\r\n    at process._tickCallback (internal/process/next_tick.js:63:19)\r\n"},{"url":"https://emirodgar.com/inbound-marketing","name":"emirodgar_com_inbound-marketing","file":"emirodgar_com_inbound-marketing.report.json","score":0,"error":"Sat, 27 Apr 2019 18:39:20 GMT ChromeLauncher Waiting for browser.\nSat, 27 Apr 2019 18:39:20 GMT ChromeLauncher Waiting for browser...\nSat, 27 Apr 2019 18:39:21 GMT ChromeLauncher Waiting for browser.....\nSat, 27 Apr 2019 18:39:22 GMT ChromeLauncher Waiting for browser.....\u001b[32m√\u001b[0m\nSat, 27 Apr 2019 18:39:42 GMT status Connecting to browser\nSat, 27 Apr 2019 18:39:44 GMT status Resetting state with about:blank\nSat, 27 Apr 2019 18:39:46 GMT status Benchmarking machine\nSat, 27 Apr 2019 18:39:46 GMT status Initializing…\nSat, 27 Apr 2019 18:39:47 GMT status Loading page & waiting for onload CSSUsage, ViewportDimensions, RuntimeExceptions, ChromeConsoleMessages, Accessibility, AnchorElements, ImageElements, LinkElements, MetaElements, ScriptElements, AppCacheManifest, Doctype, DOMStats, JSLibraries, OptimizedImages, PasswordInputsWithPreventedPaste, ResponseCompression, TagsBlockingFirstPaint, FontSize, EmbeddedContent, RobotsTxt, TapTargets\nSat, 27 Apr 2019 18:40:04 GMT status Disconnecting from browser...\nSat, 27 Apr 2019 18:40:04 GMT ChromeLauncher Killing Chrome instance 4792\nevents.js:174\r\n      throw er; // Unhandled 'error' event\r\n      ^\r\n\r\nError: read ECONNRESET\r\n    at TCP.onStreamRead (internal/stream_base_commons.js:111:27)\r\nEmitted 'error' event at:\r\n    at Socket.socketErrorListener (_http_client.js:392:9)\r\n    at Socket.emit (events.js:189:13)\r\n    at emitErrorNT (internal/streams/destroy.js:82:8)\r\n    at emitErrorAndCloseNT (internal/streams/destroy.js:50:3)\r\n    at process._tickCallback (internal/process/next_tick.js:63:19)\r\n"},{"url":"https://emirodgar.com/factores-seo","name":"emirodgar_com_factores-seo","file":"emirodgar_com_factores-seo.report.json","score":"0.68"},{"url":"https://emirodgar.com/experiencia-seo","name":"emirodgar_com_experiencia-seo","file":"emirodgar_com_experiencia-seo.report.json","score":0,"error":"Sat, 27 Apr 2019 18:41:47 GMT ChromeLauncher Waiting for browser.\nSat, 27 Apr 2019 18:41:47 GMT ChromeLauncher Waiting for browser...\nSat, 27 Apr 2019 18:41:49 GMT ChromeLauncher Waiting for browser.....\nSat, 27 Apr 2019 18:41:50 GMT ChromeLauncher Waiting for browser.......\nSat, 27 Apr 2019 18:41:50 GMT ChromeLauncher Waiting for browser.......\u001b[32m√\u001b[0m\nSat, 27 Apr 2019 18:42:15 GMT status Connecting to browser\nSat, 27 Apr 2019 18:42:19 GMT status Resetting state with about:blank\nSat, 27 Apr 2019 18:42:20 GMT status Benchmarking machine\nSat, 27 Apr 2019 18:42:21 GMT status Initializing…\nSat, 27 Apr 2019 18:42:23 GMT status Loading page & waiting for onload CSSUsage, ViewportDimensions, RuntimeExceptions, ChromeConsoleMessages, Accessibility, AnchorElements, ImageElements, LinkElements, MetaElements, ScriptElements, AppCacheManifest, Doctype, DOMStats, JSLibraries, OptimizedImages, PasswordInputsWithPreventedPaste, ResponseCompression, TagsBlockingFirstPaint, FontSize, EmbeddedContent, RobotsTxt, TapTargets\nSat, 27 Apr 2019 18:42:39 GMT status Disconnecting from browser...\nSat, 27 Apr 2019 18:42:39 GMT ChromeLauncher Killing Chrome instance 12936\nevents.js:174\r\n      throw er; // Unhandled 'error' event\r\n      ^\r\n\r\nError: read ECONNRESET\r\n    at TCP.onStreamRead (internal/stream_base_commons.js:111:27)\r\nEmitted 'error' event at:\r\n    at Socket.socketErrorListener (_http_client.js:392:9)\r\n    at Socket.emit (events.js:189:13)\r\n    at emitErrorNT (internal/streams/destroy.js:82:8)\r\n    at emitErrorAndCloseNT (internal/streams/destroy.js:50:3)\r\n    at process._tickCallback (internal/process/next_tick.js:63:19)\r\n"},{"url":"https://emirodgar.com/casos-exito-seo","name":"emirodgar_com_casos-exito-seo","file":"emirodgar_com_casos-exito-seo.report.json","score":0,"error":"Sat, 27 Apr 2019 18:43:07 GMT ChromeLauncher Waiting for browser.\nSat, 27 Apr 2019 18:43:07 GMT ChromeLauncher Waiting for browser...\nSat, 27 Apr 2019 18:43:08 GMT ChromeLauncher Waiting for browser.....\nSat, 27 Apr 2019 18:43:10 GMT ChromeLauncher Waiting for browser.......\nSat, 27 Apr 2019 18:43:11 GMT ChromeLauncher Waiting for browser.......\u001b[32m√\u001b[0m\nSat, 27 Apr 2019 18:43:34 GMT status Connecting to browser\nSat, 27 Apr 2019 18:43:38 GMT status Resetting state with about:blank\nSat, 27 Apr 2019 18:43:47 GMT status Benchmarking machine\nSat, 27 Apr 2019 18:43:49 GMT status Initializing…\nSat, 27 Apr 2019 18:43:51 GMT status Loading page & waiting for onload CSSUsage, ViewportDimensions, RuntimeExceptions, ChromeConsoleMessages, Accessibility, AnchorElements, ImageElements, LinkElements, MetaElements, ScriptElements, AppCacheManifest, Doctype, DOMStats, JSLibraries, OptimizedImages, PasswordInputsWithPreventedPaste, ResponseCompression, TagsBlockingFirstPaint, FontSize, EmbeddedContent, RobotsTxt, TapTargets\nSat, 27 Apr 2019 18:44:09 GMT status Disconnecting from browser...\nSat, 27 Apr 2019 18:44:09 GMT ChromeLauncher Killing Chrome instance 11248\nevents.js:174\r\n      throw er; // Unhandled 'error' event\r\n      ^\r\n\r\nError: read ECONNRESET\r\n    at TCP.onStreamRead (internal/stream_base_commons.js:111:27)\r\nEmitted 'error' event at:\r\n    at Socket.socketErrorListener (_http_client.js:392:9)\r\n    at Socket.emit (events.js:189:13)\r\n    at emitErrorNT (internal/streams/destroy.js:82:8)\r\n    at emitErrorAndCloseNT (internal/streams/destroy.js:50:3)\r\n    at process._tickCallback (internal/process/next_tick.js:63:19)\r\n"},{"url":"https://emirodgar.com/estrategia-seo","name":"emirodgar_com_estrategia-seo","file":"emirodgar_com_estrategia-seo.report.json","score":"0.68"},{"url":"https://emirodgar.com/posicionamiento-seo-local","name":"emirodgar_com_posicionamiento-seo-local","file":"emirodgar_com_posicionamiento-seo-local.report.json","score":0,"error":"Sat, 27 Apr 2019 18:45:54 GMT ChromeLauncher Waiting for browser.\nSat, 27 Apr 2019 18:45:54 GMT ChromeLauncher Waiting for browser...\nSat, 27 Apr 2019 18:45:56 GMT ChromeLauncher Waiting for browser.....\nSat, 27 Apr 2019 18:45:57 GMT ChromeLauncher Waiting for browser.......\nSat, 27 Apr 2019 18:45:58 GMT ChromeLauncher Waiting for browser.......\u001b[32m√\u001b[0m\nSat, 27 Apr 2019 18:46:22 GMT status Connecting to browser\nSat, 27 Apr 2019 18:46:26 GMT status Resetting state with about:blank\nSat, 27 Apr 2019 18:46:33 GMT status Benchmarking machine\nSat, 27 Apr 2019 18:46:34 GMT status Initializing…\nSat, 27 Apr 2019 18:46:35 GMT status Loading page & waiting for onload CSSUsage, ViewportDimensions, RuntimeExceptions, ChromeConsoleMessages, Accessibility, AnchorElements, ImageElements, LinkElements, MetaElements, ScriptElements, AppCacheManifest, Doctype, DOMStats, JSLibraries, OptimizedImages, PasswordInputsWithPreventedPaste, ResponseCompression, TagsBlockingFirstPaint, FontSize, EmbeddedContent, RobotsTxt, TapTargets\nSat, 27 Apr 2019 18:46:52 GMT status Disconnecting from browser...\nSat, 27 Apr 2019 18:46:52 GMT ChromeLauncher Killing Chrome instance 13452\nevents.js:174\r\n      throw er; // Unhandled 'error' event\r\n      ^\r\n\r\nError: read ECONNRESET\r\n    at TCP.onStreamRead (internal/stream_base_commons.js:111:27)\r\nEmitted 'error' event at:\r\n    at Socket.socketErrorListener (_http_client.js:392:9)\r\n    at Socket.emit (events.js:189:13)\r\n    at emitErrorNT (internal/streams/destroy.js:82:8)\r\n    at emitErrorAndCloseNT (internal/streams/destroy.js:50:3)\r\n    at process._tickCallback (internal/process/next_tick.js:63:19)\r\n"},{"url":"https://emirodgar.com/eliminar-url-google","name":"emirodgar_com_eliminar-url-google","file":"emirodgar_com_eliminar-url-google.report.json","score":0,"error":"Sat, 27 Apr 2019 18:47:19 GMT ChromeLauncher Waiting for browser.\nSat, 27 Apr 2019 18:47:19 GMT ChromeLauncher Waiting for browser...\nSat, 27 Apr 2019 18:47:20 GMT ChromeLauncher Waiting for browser.....\nSat, 27 Apr 2019 18:47:22 GMT ChromeLauncher Waiting for browser.......\nSat, 27 Apr 2019 18:47:22 GMT ChromeLauncher Waiting for browser.......\u001b[32m√\u001b[0m\nSat, 27 Apr 2019 18:47:47 GMT status Connecting to browser\nSat, 27 Apr 2019 18:47:49 GMT status Resetting state with about:blank\nSat, 27 Apr 2019 18:47:52 GMT status Benchmarking machine\nSat, 27 Apr 2019 18:47:52 GMT status Initializing…\nSat, 27 Apr 2019 18:47:54 GMT status Loading page & waiting for onload CSSUsage, ViewportDimensions, RuntimeExceptions, ChromeConsoleMessages, Accessibility, AnchorElements, ImageElements, LinkElements, MetaElements, ScriptElements, AppCacheManifest, Doctype, DOMStats, JSLibraries, OptimizedImages, PasswordInputsWithPreventedPaste, ResponseCompression, TagsBlockingFirstPaint, FontSize, EmbeddedContent, RobotsTxt, TapTargets\nSat, 27 Apr 2019 18:48:10 GMT status Disconnecting from browser...\nSat, 27 Apr 2019 18:48:10 GMT ChromeLauncher Killing Chrome instance 11736\nevents.js:174\r\n      throw er; // Unhandled 'error' event\r\n      ^\r\n\r\nError: read ECONNRESET\r\n    at TCP.onStreamRead (internal/stream_base_commons.js:111:27)\r\nEmitted 'error' event at:\r\n    at Socket.socketErrorListener (_http_client.js:392:9)\r\n    at Socket.emit (events.js:189:13)\r\n    at emitErrorNT (internal/streams/destroy.js:82:8)\r\n    at emitErrorAndCloseNT (internal/streams/destroy.js:50:3)\r\n    at process._tickCallback (internal/process/next_tick.js:63:19)\r\n"},{"url":"https://emirodgar.com/herramientas-seo-gratis","name":"emirodgar_com_herramientas-seo-gratis","file":"emirodgar_com_herramientas-seo-gratis.report.json","score":"0.68"},{"url":"https://emirodgar.com/recursos-marketing-digital","name":"emirodgar_com_recursos-marketing-digital","file":"emirodgar_com_recursos-marketing-digital.report.json","score":"0.57"},{"url":"https://emirodgar.com/posicionamiento-web-gratis/","name":"emirodgar_com_posicionamiento-web-gratis_","file":"emirodgar_com_posicionamiento-web-gratis_.report.json","score":"0.63"}]